{
  "id": "ChZDSUhNMG9nS0VJQ0FnSURodTZQT1NBEAE",
  "original_language": "hr",
  "text": "Brzo i dobro... Saljh mail-om rezultate brzi...",
  "translations": {
    "sr": "Brzo i dobro... Šalju mail-om rezultate brzo...",
    "sr_cyrl": "Брзо и добро... Шаљу мејлом резултате брзо...",
    "en": "Fast and good... They send results by email quickly...",
    "ru": "Быстро и хорошо... Результаты по почте присылают быстро...",
    "de": "Schnell und gut... Sie senden Ergebnisse schnell per E-Mail...",
    "tr": "Hızlı ve iyi... Sonuçları e-posta ile hızlıca gönderiyorlar..."
  }
}
