{
  "type": "reply",
  "id": "ChdDSUhNMG9nS0VJQ0FnSUN1cnVlVHhRRRAB",
  "original_language": "hr",
  "text": "Sanja, hvala puno na divnim riječima! 🤩 Srdačan pozdrav iz stomatoloske ordinacije Dr Filimanvić.🤗👋 …",
  "translations": {
    "sr": "Sanja, hvala puno na divnim riječima! 🤩 Srdačan pozdrav iz stomatoloske ordinacije Dr Filimanvić.🤗👋 …",
    "sr_cyrl": "Сања, хвала пуно на дивним ријечима! 🤩 Срдачан поздрав из стоматолоске ординације Др Филиманвић.🤗👋 …",
    "en": "Sanja, thank you for the wonderful words! 🤩 Kind regards from the Dr Filimanovic dental clinic.🤗👋 …",
    "ru": "Sanja, спасибо за прекрасные слова! 🤩 Привет от стоматологической клиники Dr Filimanovic.🤗👋 …",
    "de": "Sanja, vielen Dank! 🤩 Grüße, Praxis Dr Filimanovic.🤗👋 …",
    "tr": "Sanja, harika sözleriniz için teşekkürler! 🤩 Sevgilerle, Dr Filimanovic diş kliniği.🤗👋 …"
  }
}
