{
  "type": "reply",
  "id": "ChZDSUhNMG9nS0VNajZvNFRFbUxiaEpBEAE",
  "original_language": "en",
  "text": "Svetlana, thanks so much for kind words. Kind regards, dental office Filimanović.🤗 …",
  "translations": {
    "en": "Svetlana, thanks so much for kind words. Kind regards, dental office Filimanović.🤗 …",
    "sr": "Svetlana, hvala puno na lijepim riječima. Srdačan pozdrav, stomatološka ordinacija Filimanović.🤗 …",
    "sr_cyrl": "Светлана, хвала пуно на лијепим ријечима. Срдачан поздрав, стоматолошка ординација Филимановић.🤗 …",
    "ru": "Svetlana, большое спасибо за тёплые слова. С наилучшими пожеланиями, стоматологическая клиника Filimanović.🤗 …",
    "de": "Svetlana, vielen Dank für die netten Worte. Herzliche Grüße, Zahnarztpraxis Filimanović.🤗 …",
    "tr": "Svetlana, güzel sözleriniz için çok teşekkür ederiz. Sevgilerle, Filimanović diş kliniği.🤗 …"
  }
}
