{
  "type": "reply",
  "id": "ChdDSUhNMG9nS0VJQ0FnSURLejdUdnJnRRAB",
  "original_language": "hr",
  "text": "Postovani, hvala Vam na 5-ici, trudicemo se i ubuduce da zadrzimo prosjek! 😉😘 …",
  "translations": {
    "sr": "Postovani, hvala Vam na 5-ici, trudicemo se i ubuduce da zadrzimo prosjek! 😉😘 …",
    "sr_cyrl": "Постовани, хвала Вам на 5-ици, трудицемо се и убудуце да задрзимо просјек! 😉😘 …",
    "en": "Thank you for the 5 stars, we'll try to maintain the average! 😉😘 …",
    "ru": "Спасибо за 5 звёзд, постараемся поддерживать уровень! 😉😘 …",
    "de": "Danke für die 5 Sterne, wir versuchen das Niveau zu halten! 😉😘 …",
    "tr": "5 yıldız için teşekkürler, ortalamayı korumaya çalışacağız! 😉😘 …"
  }
}
