{
  "id": "ChZDSUhNMG9nS0VJQ0FnSUNackxfTldBEAE",
  "original_language": "hr",
  "text": "Izuzetna ljubaznost, profesionalnost i posvećenost. Topla preporuka svima. Dr Sladjana Filimanović.",
  "translations": {
    "sr": "Izuzetna ljubaznost, profesionalnost i posvećenost. Topla preporuka svima. Dr Sladjana Filimanović.",
    "sr_cyrl": "Изузетна љубазност, професионалност и посвећеност. Топла препорука свима. Др Сладјана Филимановић.",
    "en": "Exceptional kindness, professionalism and dedication. Warm recommendation to everyone. Dr Sladjana Filimanović.",
    "ru": "Исключительная любезность, профессионализм и преданность. Горячая рекомендация всем. Dr Sladjana Filimanović.",
    "de": "Außergewöhnliche Freundlichkeit, Professionalität und Hingabe. Herzliche Empfehlung an alle. Dr. Sladjana Filimanović.",
    "tr": "Olağanüstü nezaket, profesyonellik ve özveri. Herkese sıcak tavsiye. Dr Sladjana Filimanović."
  }
}
