{
  "clinicId": 51,
  "slug": "dental-clinic-dr-bajagic-bar",
  "name": "Dr. Bajagic — Dental Clinic",
  "cityId": 7,
  "placeId": "ChIJ64zllP9zThMRSXXzaUrPyqw",
  "regularOpeningHours": {
    "openNow": true,
    "periods": [
      {
        "open": {
          "day": 1,
          "hour": 12,
          "minute": 0
        },
        "close": {
          "day": 1,
          "hour": 20,
          "minute": 0
        }
      },
      {
        "open": {
          "day": 2,
          "hour": 12,
          "minute": 0
        },
        "close": {
          "day": 2,
          "hour": 20,
          "minute": 0
        }
      },
      {
        "open": {
          "day": 3,
          "hour": 12,
          "minute": 0
        },
        "close": {
          "day": 3,
          "hour": 20,
          "minute": 0
        }
      },
      {
        "open": {
          "day": 4,
          "hour": 12,
          "minute": 0
        },
        "close": {
          "day": 4,
          "hour": 20,
          "minute": 0
        }
      },
      {
        "open": {
          "day": 5,
          "hour": 12,
          "minute": 0
        },
        "close": {
          "day": 5,
          "hour": 20,
          "minute": 0
        }
      }
    ],
    "weekdayDescriptions": [
      "Monday: 12:00 – 8:00 PM",
      "Tuesday: 12:00 – 8:00 PM",
      "Wednesday: 12:00 – 8:00 PM",
      "Thursday: 12:00 – 8:00 PM",
      "Friday: 12:00 – 8:00 PM",
      "Saturday: Closed",
      "Sunday: Closed"
    ],
    "nextCloseTime": "2026-05-07T18:00:00Z"
  }
}