{
  "page": 38,
  "count": 43,
  "items": [
    {
      "code": "K03056",
      "version": 1,
      "name_sr_lat": "BAKTERIOLOŠKO ISPITIVANJE PERIKARDIJALNE TEČNOSTI - AEROBNO",
      "price_eur": 20.73,
      "page": 38,
      "section_letter": "K",
      "section_letter_title": "CENTAR ZA DIJAGNOSTIKU - MIKROBIOLOŠKA DIJAGNOSTIKA",
      "section_code": "K03",
      "section_title": "MIKROBIOLOŠKA DIJAGNOSTIKA"
    },
    {
      "code": "K03057",
      "version": 1,
      "name_sr_lat": "BAKTERIOLOŠKO ISPITIVANJE PERITONEALNE TEČNOSTI - AEROBNO",
      "price_eur": 20.73,
      "page": 38,
      "section_letter": "K",
      "section_letter_title": "CENTAR ZA DIJAGNOSTIKU - MIKROBIOLOŠKA DIJAGNOSTIKA",
      "section_code": "K03",
      "section_title": "MIKROBIOLOŠKA DIJAGNOSTIKA"
    },
    {
      "code": "K03058",
      "version": 1,
      "name_sr_lat": "BAKTERIOLOŠKO ISPITIVANJE SADRŽAJA ADNEKSA - AEROBNO",
      "price_eur": 20.73,
      "page": 38,
      "section_letter": "K",
      "section_letter_title": "CENTAR ZA DIJAGNOSTIKU - MIKROBIOLOŠKA DIJAGNOSTIKA",
      "section_code": "K03",
      "section_title": "MIKROBIOLOŠKA DIJAGNOSTIKA"
    },
    {
      "code": "K03059",
      "version": 1,
      "name_sr_lat": "BAKTERIOLOŠKO ISPITIVANJE SADRŽAJA DRENA - AEROBNO",
      "price_eur": 20.73,
      "page": 38,
      "section_letter": "K",
      "section_letter_title": "CENTAR ZA DIJAGNOSTIKU - MIKROBIOLOŠKA DIJAGNOSTIKA",
      "section_code": "K03",
      "section_title": "MIKROBIOLOŠKA DIJAGNOSTIKA"
    },
    {
      "code": "K03060",
      "version": 1,
      "name_sr_lat": "BAKTERIOLOŠKO ISPITIVANJE SEKRETA IZ SREDNJEG UVA - AEROBNO",
      "price_eur": 20.73,
      "page": 38,
      "section_letter": "K",
      "section_letter_title": "CENTAR ZA DIJAGNOSTIKU - MIKROBIOLOŠKA DIJAGNOSTIKA",
      "section_code": "K03",
      "section_title": "MIKROBIOLOŠKA DIJAGNOSTIKA"
    },
    {
      "code": "K03061",
      "version": 1,
      "name_sr_lat": "BAKTER. ISPITIV. URETROPROSTATIČNOG SEKRETA - AEROBNO",
      "price_eur": 20.73,
      "page": 38,
      "section_letter": "K",
      "section_letter_title": "CENTAR ZA DIJAGNOSTIKU - MIKROBIOLOŠKA DIJAGNOSTIKA",
      "section_code": "K03",
      "section_title": "MIKROBIOLOŠKA DIJAGNOSTIKA"
    },
    {
      "code": "K03062",
      "version": 1,
      "name_sr_lat": "BAKTERIOLOŠKO ISPITIVANJE URINA (NEFROSTOME) - AEROBNO",
      "price_eur": 13.32,
      "page": 38,
      "section_letter": "K",
      "section_letter_title": "CENTAR ZA DIJAGNOSTIKU - MIKROBIOLOŠKA DIJAGNOSTIKA",
      "section_code": "K03",
      "section_title": "MIKROBIOLOŠKA DIJAGNOSTIKA"
    },
    {
      "code": "K03063",
      "version": 1,
      "name_sr_lat": "BAKTER. ISPITIVANJE VRHA ARTERIJSKOG KATETERA - AEROBNO",
      "price_eur": 13.32,
      "page": 38,
      "section_letter": "K",
      "section_letter_title": "CENTAR ZA DIJAGNOSTIKU - MIKROBIOLOŠKA DIJAGNOSTIKA",
      "section_code": "K03",
      "section_title": "MIKROBIOLOŠKA DIJAGNOSTIKA"
    },
    {
      "code": "K03064",
      "version": 1,
      "name_sr_lat": "BAKTER. ISPITIVANJE VRHA ASPIRACIONOG KATETERA - AEROBNO",
      "price_eur": 13.32,
      "page": 38,
      "section_letter": "K",
      "section_letter_title": "CENTAR ZA DIJAGNOSTIKU - MIKROBIOLOŠKA DIJAGNOSTIKA",
      "section_code": "K03",
      "section_title": "MIKROBIOLOŠKA DIJAGNOSTIKA"
    },
    {
      "code": "K03065",
      "version": 1,
      "name_sr_lat": "BAKTERIOLOŠKO ISPITIVANJE BRISA BRONHOSKOPA - AEROBNO",
      "price_eur": 13.32,
      "page": 38,
      "section_letter": "K",
      "section_letter_title": "CENTAR ZA DIJAGNOSTIKU - MIKROBIOLOŠKA DIJAGNOSTIKA",
      "section_code": "K03",
      "section_title": "MIKROBIOLOŠKA DIJAGNOSTIKA"
    },
    {
      "code": "K03066",
      "version": 1,
      "name_sr_lat": "BAKTER. ISPITIV. VRHA CENTRALNOG VENSKOG KATETERA - AEROBNO",
      "price_eur": 13.32,
      "page": 38,
      "section_letter": "K",
      "section_letter_title": "CENTAR ZA DIJAGNOSTIKU - MIKROBIOLOŠKA DIJAGNOSTIKA",
      "section_code": "K03",
      "section_title": "MIKROBIOLOŠKA DIJAGNOSTIKA"
    },
    {
      "code": "K03067",
      "version": 1,
      "name_sr_lat": "BAKTERIOLOŠKO ISPITIVANJE ŽELUDAČNOG SADRŽAJA - AEROBNO",
      "price_eur": 20.73,
      "page": 38,
      "section_letter": "K",
      "section_letter_title": "CENTAR ZA DIJAGNOSTIKU - MIKROBIOLOŠKA DIJAGNOSTIKA",
      "section_code": "K03",
      "section_title": "MIKROBIOLOŠKA DIJAGNOSTIKA"
    },
    {
      "code": "K03068",
      "version": 1,
      "name_sr_lat": "BAKTERIOLOŠKO ISPITIVANJE SINOVIJALNE TEČNOSTI - AEROBNO",
      "price_eur": 20.73,
      "page": 38,
      "section_letter": "K",
      "section_letter_title": "CENTAR ZA DIJAGNOSTIKU - MIKROBIOLOŠKA DIJAGNOSTIKA",
      "section_code": "K03",
      "section_title": "MIKROBIOLOŠKA DIJAGNOSTIKA"
    },
    {
      "code": "K03069",
      "version": 1,
      "name_sr_lat": "BAKTERIOLOŠKO ISPITIVANJE OTVORA KANILE - AEROBNO",
      "price_eur": 13.32,
      "page": 38,
      "section_letter": "K",
      "section_letter_title": "CENTAR ZA DIJAGNOSTIKU - MIKROBIOLOŠKA DIJAGNOSTIKA",
      "section_code": "K03",
      "section_title": "MIKROBIOLOŠKA DIJAGNOSTIKA"
    },
    {
      "code": "K03070",
      "version": 1,
      "name_sr_lat": "BAKTERIOLOŠKO ISPITIVANJE DIJALIZNE TEČNOSTI - AEROBNO",
      "price_eur": 20.73,
      "page": 38,
      "section_letter": "K",
      "section_letter_title": "CENTAR ZA DIJAGNOSTIKU - MIKROBIOLOŠKA DIJAGNOSTIKA",
      "section_code": "K03",
      "section_title": "MIKROBIOLOŠKA DIJAGNOSTIKA"
    },
    {
      "code": "K03071",
      "version": 1,
      "name_sr_lat": "BAKTERIOLOŠKO ISPITIVANJE ISJEČKA TKIVA - AEROBNO",
      "price_eur": 20.73,
      "page": 38,
      "section_letter": "K",
      "section_letter_title": "CENTAR ZA DIJAGNOSTIKU - MIKROBIOLOŠKA DIJAGNOSTIKA",
      "section_code": "K03",
      "section_title": "MIKROBIOLOŠKA DIJAGNOSTIKA"
    },
    {
      "code": "K03072",
      "version": 1,
      "name_sr_lat": "BAKTERIOLOŠKO ISPITIVANJE TKIVA POSTELJICE - AEROBNO",
      "price_eur": 20.73,
      "page": 38,
      "section_letter": "K",
      "section_letter_title": "CENTAR ZA DIJAGNOSTIKU - MIKROBIOLOŠKA DIJAGNOSTIKA",
      "section_code": "K03",
      "section_title": "MIKROBIOLOŠKA DIJAGNOSTIKA"
    },
    {
      "code": "K03073",
      "version": 1,
      "name_sr_lat": "ISPIT.PRIS. BORDATEL.PERTUS. IZ BRISA NAZOFARINKSA - AEROBNO",
      "price_eur": 13.32,
      "page": 38,
      "section_letter": "K",
      "section_letter_title": "CENTAR ZA DIJAGNOSTIKU - MIKROBIOLOŠKA DIJAGNOSTIKA",
      "section_code": "K03",
      "section_title": "MIKROBIOLOŠKA DIJAGNOSTIKA"
    },
    {
      "code": "K03074",
      "version": 1,
      "name_sr_lat": "ISPIT.PRIS. SOLUBILN. BAKT.ANTIG. U LIKVORU - LATEX AGLUTIN.",
      "price_eur": 4.29,
      "page": 38,
      "section_letter": "K",
      "section_letter_title": "CENTAR ZA DIJAGNOSTIKU - MIKROBIOLOŠKA DIJAGNOSTIKA",
      "section_code": "K03",
      "section_title": "MIKROBIOLOŠKA DIJAGNOSTIKA"
    },
    {
      "code": "K03075",
      "version": 1,
      "name_sr_lat": "ISPITIVANJE PRISUSTVA VIBRIO CHOLLERAE - AEROBNO",
      "price_eur": 13.32,
      "page": 38,
      "section_letter": "K",
      "section_letter_title": "CENTAR ZA DIJAGNOSTIKU - MIKROBIOLOŠKA DIJAGNOSTIKA",
      "section_code": "K03",
      "section_title": "MIKROBIOLOŠKA DIJAGNOSTIKA"
    },
    {
      "code": "K03076",
      "version": 1,
      "name_sr_lat": "BAKTERIOLOŠKO ISPITIVANJE BRISA TANKOG CRIJEVA - ANAEROBNO",
      "price_eur": 17.31,
      "page": 38,
      "section_letter": "K",
      "section_letter_title": "CENTAR ZA DIJAGNOSTIKU - MIKROBIOLOŠKA DIJAGNOSTIKA",
      "section_code": "K03",
      "section_title": "MIKROBIOLOŠKA DIJAGNOSTIKA"
    },
    {
      "code": "K03077",
      "version": 1,
      "name_sr_lat": "BAKTERIOLOŠKO ISPITIVANJE BRISA TORAKALNOG DRENA - ANAEROBNO",
      "price_eur": 17.31,
      "page": 38,
      "section_letter": "K",
      "section_letter_title": "CENTAR ZA DIJAGNOSTIKU - MIKROBIOLOŠKA DIJAGNOSTIKA",
      "section_code": "K03",
      "section_title": "MIKROBIOLOŠKA DIJAGNOSTIKA"
    },
    {
      "code": "K03078",
      "version": 1,
      "name_sr_lat": "BAKTERIOLOŠKO ISPITIVANJE BRISA OVOJNICE CRIJEVA - ANAEROBNO",
      "price_eur": 17.31,
      "page": 38,
      "section_letter": "K",
      "section_letter_title": "CENTAR ZA DIJAGNOSTIKU - MIKROBIOLOŠKA DIJAGNOSTIKA",
      "section_code": "K03",
      "section_title": "MIKROBIOLOŠKA DIJAGNOSTIKA"
    },
    {
      "code": "K03079",
      "version": 1,
      "name_sr_lat": "BAKTERIOLOŠKO ISPITIVANJE BRISA PERITONEUMA - ANAEROBNO",
      "price_eur": 17.31,
      "page": 38,
      "section_letter": "K",
      "section_letter_title": "CENTAR ZA DIJAGNOSTIKU - MIKROBIOLOŠKA DIJAGNOSTIKA",
      "section_code": "K03",
      "section_title": "MIKROBIOLOŠKA DIJAGNOSTIKA"
    },
    {
      "code": "K03080",
      "version": 1,
      "name_sr_lat": "BAKTER. ISPITIVANJE BRISA ABDOMINALNOG DRENA - ANAEROBNO",
      "price_eur": 17.31,
      "page": 38,
      "section_letter": "K",
      "section_letter_title": "CENTAR ZA DIJAGNOSTIKU - MIKROBIOLOŠKA DIJAGNOSTIKA",
      "section_code": "K03",
      "section_title": "MIKROBIOLOŠKA DIJAGNOSTIKA"
    },
    {
      "code": "K03081",
      "version": 1,
      "name_sr_lat": "BAKTERIOLOŠKO ISPITIVANJE BRISA RANE - ANAEROBNO",
      "price_eur": 17.31,
      "page": 38,
      "section_letter": "K",
      "section_letter_title": "CENTAR ZA DIJAGNOSTIKU - MIKROBIOLOŠKA DIJAGNOSTIKA",
      "section_code": "K03",
      "section_title": "MIKROBIOLOŠKA DIJAGNOSTIKA"
    },
    {
      "code": "K03082",
      "version": 1,
      "name_sr_lat": "BAKTERIOLOŠKO ISPITIVANJE SADRŽAJA ABSCESA - ANAEROBNO",
      "price_eur": 24.63,
      "page": 38,
      "section_letter": "K",
      "section_letter_title": "CENTAR ZA DIJAGNOSTIKU - MIKROBIOLOŠKA DIJAGNOSTIKA",
      "section_code": "K03",
      "section_title": "MIKROBIOLOŠKA DIJAGNOSTIKA"
    },
    {
      "code": "K03083",
      "version": 1,
      "name_sr_lat": "BAKTERIOLOŠKO ISPITIVANJE BRISA IZ CAVUM UTERUSA - ANAEROBNO",
      "price_eur": 17.31,
      "page": 38,
      "section_letter": "K",
      "section_letter_title": "CENTAR ZA DIJAGNOSTIKU - MIKROBIOLOŠKA DIJAGNOSTIKA",
      "section_code": "K03",
      "section_title": "MIKROBIOLOŠKA DIJAGNOSTIKA"
    },
    {
      "code": "K03084",
      "version": 1,
      "name_sr_lat": "BAKTERIOLOŠKO ISPITIVANJE SADRŽAJA ADNEKSA - ANAEROBNO",
      "price_eur": 24.63,
      "page": 38,
      "section_letter": "K",
      "section_letter_title": "CENTAR ZA DIJAGNOSTIKU - MIKROBIOLOŠKA DIJAGNOSTIKA",
      "section_code": "K03",
      "section_title": "MIKROBIOLOŠKA DIJAGNOSTIKA"
    },
    {
      "code": "K03085",
      "version": 1,
      "name_sr_lat": "BAKTERIOLOŠKO ISPITIVANJE KRVI - ANAEROBNO",
      "price_eur": 17.31,
      "page": 38,
      "section_letter": "K",
      "section_letter_title": "CENTAR ZA DIJAGNOSTIKU - MIKROBIOLOŠKA DIJAGNOSTIKA",
      "section_code": "K03",
      "section_title": "MIKROBIOLOŠKA DIJAGNOSTIKA"
    },
    {
      "code": "K03086",
      "version": 1,
      "name_sr_lat": "BAKTERIOLOŠKO ISPITIVANJE ISJEČKA TKIVA - ANAEROBNO",
      "price_eur": 24.63,
      "page": 38,
      "section_letter": "K",
      "section_letter_title": "CENTAR ZA DIJAGNOSTIKU - MIKROBIOLOŠKA DIJAGNOSTIKA",
      "section_code": "K03",
      "section_title": "MIKROBIOLOŠKA DIJAGNOSTIKA"
    },
    {
      "code": "K03087",
      "version": 1,
      "name_sr_lat": "BAKTERIOLOŠKO ISPITIVANJE ISJEČKA POSTELJICE - ANAEROBNO",
      "price_eur": 24.63,
      "page": 38,
      "section_letter": "K",
      "section_letter_title": "CENTAR ZA DIJAGNOSTIKU - MIKROBIOLOŠKA DIJAGNOSTIKA",
      "section_code": "K03",
      "section_title": "MIKROBIOLOŠKA DIJAGNOSTIKA"
    },
    {
      "code": "K03088",
      "version": 1,
      "name_sr_lat": "BAKTERIOLOŠKO ISPITIVANJE BRISA KRVI - ANAEROBNO",
      "price_eur": 17.31,
      "page": 38,
      "section_letter": "K",
      "section_letter_title": "CENTAR ZA DIJAGNOSTIKU - MIKROBIOLOŠKA DIJAGNOSTIKA",
      "section_code": "K03",
      "section_title": "MIKROBIOLOŠKA DIJAGNOSTIKA"
    },
    {
      "code": "K03089",
      "version": 1,
      "name_sr_lat": "BAKTERIOLOŠKO ISPITIVANJE BRISA DEBELOG CRIJEVA - ANAEROBNO",
      "price_eur": 17.31,
      "page": 38,
      "section_letter": "K",
      "section_letter_title": "CENTAR ZA DIJAGNOSTIKU - MIKROBIOLOŠKA DIJAGNOSTIKA",
      "section_code": "K03",
      "section_title": "MIKROBIOLOŠKA DIJAGNOSTIKA"
    },
    {
      "code": "K03090",
      "version": 1,
      "name_sr_lat": "BAKTERIOLOŠKO ISPITIVANJE PERITONEALNE TEČNOSTI - ANAEROBNO",
      "price_eur": 24.63,
      "page": 38,
      "section_letter": "K",
      "section_letter_title": "CENTAR ZA DIJAGNOSTIKU - MIKROBIOLOŠKA DIJAGNOSTIKA",
      "section_code": "K03",
      "section_title": "MIKROBIOLOŠKA DIJAGNOSTIKA"
    },
    {
      "code": "K03091",
      "version": 1,
      "name_sr_lat": "BAKTERIOLOŠKO ISPITIVANJE SADRŽAJA DRENA - ANAEROBNO",
      "price_eur": 24.63,
      "page": 38,
      "section_letter": "K",
      "section_letter_title": "CENTAR ZA DIJAGNOSTIKU - MIKROBIOLOŠKA DIJAGNOSTIKA",
      "section_code": "K03",
      "section_title": "MIKROBIOLOŠKA DIJAGNOSTIKA"
    },
    {
      "code": "K03092",
      "version": 1,
      "name_sr_lat": "ISPITIVANJE PRISUSTVA ECHINOCOCCUS SPP. - BOJENI PREPARAT",
      "price_eur": 12.93,
      "page": 38,
      "section_letter": "K",
      "section_letter_title": "CENTAR ZA DIJAGNOSTIKU - MIKROBIOLOŠKA DIJAGNOSTIKA",
      "section_code": "K03",
      "section_title": "MIKROBIOLOŠKA DIJAGNOSTIKA"
    },
    {
      "code": "K03093",
      "version": 1,
      "name_sr_lat": "ISPITIVANJE PRISUSTVA ECHINOCOCCUS SPP. - NATIVNI PREPARAT",
      "price_eur": 12.93,
      "page": 38,
      "section_letter": "K",
      "section_letter_title": "CENTAR ZA DIJAGNOSTIKU - MIKROBIOLOŠKA DIJAGNOSTIKA",
      "section_code": "K03",
      "section_title": "MIKROBIOLOŠKA DIJAGNOSTIKA"
    },
    {
      "code": "K03094",
      "version": 1,
      "name_sr_lat": "ISPITIV. PRISUST. BABESIA SPP. - BOJENI PREPARAT GUSTE KAPI",
      "price_eur": 33.3,
      "page": 38,
      "section_letter": "K",
      "section_letter_title": "CENTAR ZA DIJAGNOSTIKU - MIKROBIOLOŠKA DIJAGNOSTIKA",
      "section_code": "K03",
      "section_title": "MIKROBIOLOŠKA DIJAGNOSTIKA"
    },
    {
      "code": "K03095",
      "version": 1,
      "name_sr_lat": "ISPITIV. PRIS. BABESIA SPP. - BOJENI PREPARAT KRVNOG RAZMAZA",
      "price_eur": 33.3,
      "page": 38,
      "section_letter": "K",
      "section_letter_title": "CENTAR ZA DIJAGNOSTIKU - MIKROBIOLOŠKA DIJAGNOSTIKA",
      "section_code": "K03",
      "section_title": "MIKROBIOLOŠKA DIJAGNOSTIKA"
    },
    {
      "code": "K03096",
      "version": 1,
      "name_sr_lat": "ISPITIVANJE PRISUSTVA CRYPTOCOCCUS SPP. - KULTIVACIJA",
      "price_eur": 13.32,
      "page": 38,
      "section_letter": "K",
      "section_letter_title": "CENTAR ZA DIJAGNOSTIKU - MIKROBIOLOŠKA DIJAGNOSTIKA",
      "section_code": "K03",
      "section_title": "MIKROBIOLOŠKA DIJAGNOSTIKA"
    },
    {
      "code": "K03097",
      "version": 1,
      "name_sr_lat": "ISPITIVANJE PRISUSTVA CRYPTOCOCCUS SPP. - BOJENI PREPARAT",
      "price_eur": 13.32,
      "page": 38,
      "section_letter": "K",
      "section_letter_title": "CENTAR ZA DIJAGNOSTIKU - MIKROBIOLOŠKA DIJAGNOSTIKA",
      "section_code": "K03",
      "section_title": "MIKROBIOLOŠKA DIJAGNOSTIKA"
    },
    {
      "code": "K03098",
      "version": 1,
      "name_sr_lat": "ISPITIVANJE PRISUSTVA CRYPTOCOCCUS SPP. - TUŠ PREPARAT",
      "price_eur": 13.32,
      "page": 38,
      "section_letter": "K",
      "section_letter_title": "CENTAR ZA DIJAGNOSTIKU - MIKROBIOLOŠKA DIJAGNOSTIKA",
      "section_code": "K03",
      "section_title": "MIKROBIOLOŠKA DIJAGNOSTIKA"
    }
  ]
}