{
  "id": "ChdDSUhNMG9nS0VJQ0FnSUNEblktMGdBRRAB",
  "original_language": "ru",
  "text": "Отличная стоматология, есть все необходимое оборудование и врачи квалифицированные. Всегда помогают, идут на встречу.",
  "translations": {
    "sr": "Odlična stomatologija, ima sva neophodna oprema i kvalifikovani lekari. Uvek pomažu, izlaze u susret.",
    "sr_cyrl": "Одлична стоматологија, има сва неопходна опрема и квалификовани лекари. Увек помажу, излазе у сусрет.",
    "en": "Excellent dental clinic, all the necessary equipment is available and the doctors are qualified. They always help and accommodate.",
    "ru": "Отличная стоматология, есть все необходимое оборудование и врачи квалифицированные. Всегда помогают, идут на встречу.",
    "de": "Ausgezeichnete Zahnklinik, alle notwendigen Geräte sind vorhanden und die Ärzte sind qualifiziert. Sie helfen immer und kommen entgegen.",
    "tr": "Mükemmel diş kliniği, tüm gerekli ekipman mevcut ve doktorlar nitelikli. Her zaman yardım ediyorlar, karşılıyorlar."
  }
}
