{
  "id": "ChZDSUhNMG9nS0VJQ0FnSUNEaW9iaGF3EAE",
  "original_language": "hr",
  "text": "Znanje i opremljenost za svaku pohvalu!",
  "translations": {
    "sr": "Znanje i opremljenost za svaku pohvalu!",
    "sr_cyrl": "Знање и опремљеност за сваку похвалу!",
    "en": "The knowledge and equipment deserve every praise!",
    "ru": "Знания и оснащение заслуживают всяческих похвал!",
    "de": "Das Wissen und die Ausstattung verdienen jedes Lob!",
    "tr": "Bilgi ve donanım her türlü övgüyü hak ediyor!"
  }
}