{
  "id": "ChZDSUhNMG9nS0VJQ0FnTURRblpIS053EAE",
  "original_language": "bs",
  "text": "Brzo sam se oporavila od povrede skocnog zgloba! Preporucujem svima.",
  "translations": {
    "sr": "Brzo sam se oporavila od povrede skočnog zgloba! Preporučujem svima.",
    "sr_cyrl": "Брзо сам се опоравила од повреде скочног зглоба! Препоручујем свима.",
    "en": "I recovered quickly from my ankle injury! I recommend it to everyone.",
    "ru": "Я быстро восстановилась от травмы голеностопного сустава! Рекомендую всем.",
    "de": "Ich erholte mich schnell von meiner Sprunggelenksverletzung! Ich empfehle es allen.",
    "tr": "Ayak bileği yaralanmamdan hızla iyileştim! Herkese tavsiye ederim."
  }
}