{
  "id": "ChZDSUhNMG9nS0VJQ0FnSURCeFpmaEpREAE",
  "original_language": "hr",
  "text": "Osoblje ljubazno i profisionalno obavljaju svoj posao.",
  "translations": {
    "sr": "Osoblje ljubazno i profesionalno obavljaju svoj posao.",
    "sr_cyrl": "Особље љубазно и професионално обављају свој посао.",
    "en": "The staff is kind and professionally does their job.",
    "ru": "Персонал любезный и профессионально выполняет свою работу.",
    "de": "Das Personal ist freundlich und erledigt seine Arbeit professionell.",
    "tr": "Personel nazik ve işlerini profesyonelce yapıyor."
  }
}
