{
  "id": "ChZDSUhNMG9nS0VJQ0FnTURJbVlMalR3EAE",
  "original_language": "hr",
  "text": "Profesionalni i ljubazni!Sve pohvale!!🙂 …",
  "translations": {
    "sr": "Profesionalni i ljubazni! Sve pohvale!! 🙂 …",
    "sr_cyrl": "Професионални и љубазни! Све похвале!! 🙂 …",
    "en": "Professional and kind! All praise!! 🙂 …",
    "ru": "Профессиональные и любезные! Всяческие похвалы!! 🙂 …",
    "de": "Professionell und freundlich! Alle Achtung!! 🙂 …",
    "tr": "Profesyonel ve nazikler! Her türlü övgüyü hak ediyorlar!! 🙂 …"
  }
}
