{
  "id": "ChdDSUhNMG9nS0VJQ0FnSUNSaG95TjBnRRAB",
  "original_language": "ru",
  "text": "Были на консультации у хирурга. Неудовлетворительно. Не рекомендую. Потеря времени и денег.",
  "translations": {
    "sr": "Bili smo na konsultaciji kod hirurga. Nezadovoljavajuće. Ne preporučujem. Gubitak vremena i novca.",
    "sr_cyrl": "Били смо на консултацији код хирурга. Незадовољавајуће. Не препоручујем. Губитак времена и новца.",
    "en": "We had a consultation with a surgeon. Unsatisfactory. I do not recommend. A waste of time and money.",
    "ru": "Были на консультации у хирурга. Неудовлетворительно. Не рекомендую. Потеря времени и денег.",
    "de": "Wir waren bei einer Beratung beim Chirurgen. Unbefriedigend. Ich empfehle es nicht. Zeit- und Geldverschwendung.",
    "tr": "Cerrahla konsültasyonda bulunduk. Tatmin edici değil. Tavsiye etmiyorum. Zaman ve para kaybı."
  }
}
