{
  "id": "ChdDSUhNMG9nS0VJQ0FnSUR2XzZhV3BBRRAB",
  "original_language": "ru",
  "text": "Лаборатория не понравилась, сделали неправильный анализ ребенку",
  "translations": {
    "sr": "Laboratorija mi se nije dopala, napravili su pogrešnu analizu detetu",
    "sr_cyrl": "Лабораторија ми се није допала, направили су погрешну анализу детету",
    "en": "I didn't like the laboratory, they made an incorrect analysis for the child",
    "ru": "Лаборатория не понравилась, сделали неправильный анализ ребенку",
    "de": "Das Labor hat mir nicht gefallen, sie haben eine falsche Analyse für das Kind gemacht",
    "tr": "Laboratuvarı beğenmedim, çocuk için yanlış analiz yaptılar"
  }
}
