{
  "id": "Ci9DQUlRQUNvZENodHljRjlvT25VeFdWSlVPR0ZDUmpKTFNETmZNRTVxUzFkUVIzYxAB",
  "original_language": "hr",
  "text": "Uvjek najbolji i najprijatniji za rad ❤️ Dr Dragana Bjelica fenomenalna a sestra Danka preljubazna 🥰❤️ …",
  "translations": {
    "sr": "Uvjek najbolji i najprijatniji za rad ❤️ Dr Dragana Bjelica fenomenalna a sestra Danka preljubazna 🥰❤️ …",
    "sr_cyrl": "Увијек најбољи и најпријатнији за рад ❤️ Dr Dragana Bjelica феноменална а сестра Данка прељубазна 🥰❤️ …",
    "en": "Always the best and the most pleasant to work with ❤️ Dr Dragana Bjelica is phenomenal and nurse Danka is very kind 🥰❤️ …",
    "ru": "Всегда лучшие и самые приятные в работе ❤️ Dr Dragana Bjelica феноменальна, а медсестра Данка прелюбезна 🥰❤️ …",
    "de": "Immer die Besten und Angenehmsten bei der Arbeit ❤️ Dr. Dragana Bjelica ist phänomenal und Schwester Danka ist sehr freundlich 🥰❤️ …",
    "tr": "Her zaman en iyiler ve çalışmada en hoşlar ❤️ Dr Dragana Bjelica olağanüstü ve hemşire Danka çok güler yüzlü 🥰❤️ …"
  }
}
