{
  "id": "Ci9DQUlRQUNvZENodHljRjlvT25ac1FubFVSMFExWkVOS1NsRlhiRXBMT0hkeVJFRRAB",
  "original_language": "bs",
  "text": "Jako ljubazna i profesionalna dr Dragana i njene asistentkinje, pruzaju sigurnost i kvalitet u radu!",
  "translations": {
    "sr": "Jako ljubazna i profesionalna dr Dragana i njene asistentkinje, pruzaju sigurnost i kvalitet u radu!",
    "sr_cyrl": "Јако љубазна и професионална др Драгана и њене асистенткиње, пружају сигурност и квалитет у раду!",
    "en": "Very kind and professional Dr. Dragana and her assistants, providing safety and quality in their work!",
    "ru": "Очень любезная и профессиональная др Драгана и её ассистентки, обеспечивают безопасность и качество в работе!",
    "de": "Sehr freundliche und professionelle Dr. Dragana und ihre Assistentinnen, die Sicherheit und Qualität in der Arbeit bieten!",
    "tr": "Çok nazik ve profesyonel Dr. Dragana ve asistanları, çalışmalarında güvenlik ve kalite sunuyorlar!"
  }
}
