{
  "id": "Ci9DQUlRQUNvZENodHljRjlvT2xwbVFuWlZMWE5TWWpOSFNuZFZWRloyTTFaVmNuYxAB",
  "original_language": "hr",
  "text": "Brz dogovor, odmah dobili termin za pregled, brzo resen problem. Preporuka 👍🏻 …",
  "translations": {
    "sr": "Brz dogovor, odmah dobili termin za pregled, brzo rešen problem. Preporuka 👍🏻 …",
    "sr_cyrl": "Брз договор, одмах добили термин за преглед, брзо решен проблем. Препорука 👍🏻 …",
    "en": "Quick agreement, we immediately got an appointment for the examination, the problem was resolved quickly. Recommended 👍🏻 …",
    "ru": "Быстрая договорённость, сразу получили запись на осмотр, проблема быстро решена. Рекомендую 👍🏻 …",
    "de": "Schnelle Vereinbarung, wir haben sofort einen Termin für die Untersuchung bekommen, das Problem wurde schnell gelöst. Empfehlung 👍🏻 …",
    "tr": "Hızlı anlaşma, hemen muayene için randevu aldık, sorun hızla çözüldü. Tavsiye ederim 👍🏻 …"
  }
}
