{
  "id": "ChIJwU5wPeATThMRqN_0iTEpFrQ",
  "types": [
    "doctor",
    "point_of_interest",
    "health",
    "establishment"
  ],
  "formattedAddress": "56 Rr. Nënë Tereza, Ulcinj 85360, Црна Гора",
  "location": {
    "latitude": 41.927398499999995,
    "longitude": 19.2269474
  },
  "googleMapsUri": "https://maps.google.com/?cid=12976604669059325864&g_mp=Cilnb29nbGUubWFwcy5wbGFjZXMudjEuUGxhY2VzLlNlYXJjaE5lYXJieRACGAQgAA",
  "displayName": {
    "text": "Ordinacija ultra zvuk Ulcinj",
    "languageCode": "sr"
  },
  "_searchType": "doctor"
}