{
  "id": "ChIJ64zllP9zThMRSXXzaUrPyqw",
  "types": [
    "dentist",
    "health",
    "point_of_interest",
    "establishment"
  ],
  "internationalPhoneNumber": "+382 30 312 745",
  "formattedAddress": "Maršala Tita, Bar, Црна Гора",
  "location": {
    "latitude": 42.0965394,
    "longitude": 19.0945063
  },
  "rating": 4.3,
  "googleMapsUri": "https://maps.google.com/?cid=12450992038331249993&g_mp=Cilnb29nbGUubWFwcy5wbGFjZXMudjEuUGxhY2VzLlNlYXJjaE5lYXJieRACGAQgAA",
  "userRatingCount": 6,
  "displayName": {
    "text": "Dental Clinic dr. Bajagic",
    "languageCode": "ru"
  },
  "reviews": [
    {
      "name": "places/ChIJ64zllP9zThMRSXXzaUrPyqw/reviews/Ci9DQUlRQUNvZENodHljRjlvT2w5b1EyNVpjVlJRY0VSSlpIbEVVWEV0UjI4emMyYxAB",
      "relativePublishTimeDescription": "пре недељу дана",
      "rating": 1,
      "text": {
        "text": "Веома су лоши, а хигијена је ужасна...",
        "languageCode": "sr"
      },
      "originalText": {
        "text": "Jako su loši, i higijena je očajna...",
        "languageCode": "hr"
      },
      "authorAttribution": {
        "displayName": "Koki Koki",
        "uri": "https://www.google.com/maps/contrib/100263514228679500280/reviews",
        "photoUri": "https://lh3.googleusercontent.com/a-/ALV-UjU8lxLAnqe0FhYI2IAUBxrVlK7nuLRCxg5PHSSeBzXnYlU5xFEo=s128-c0x00000000-cc-rp-mo"
      },
      "publishTime": "2026-03-04T15:09:07.407809842Z",
      "flagContentUri": "https://www.google.com/local/content/rap/report?postId=Ci9DQUlRQUNvZENodHljRjlvT2w5b1EyNVpjVlJRY0VSSlpIbEVVWEV0UjI4emMyYxAB&d=17924085&t=1",
      "googleMapsUri": "https://www.google.com/maps/reviews/data=!4m6!14m5!1m4!2m3!1sCi9DQUlRQUNvZENodHljRjlvT2w5b1EyNVpjVlJRY0VSSlpIbEVVWEV0UjI4emMyYxAB!2m1!1s0x134e73ff94e58ceb:0xaccacf4a69f37549"
    },
    {
      "name": "places/ChIJ64zllP9zThMRSXXzaUrPyqw/reviews/ChdDSUhNMG9nS0VJQ0FnSUNjeThPSDZ3RRAB",
      "relativePublishTimeDescription": "пре 5 година",
      "rating": 5,
      "text": {
        "text": "Они су увек ту за своје пацијенте, чак и током пандемије ЦОВИД-19. Наравно, поштујући све мере и процедуре у припреми пацијента, ординације и њих самих. Све похвале! 👏🏻",
        "languageCode": "sr"
      },
      "originalText": {
        "text": "Uvjek su tu za svoje pacijente, pa i u vrijeme pandemije COVID-a 19. Naravno poštujući sve mjere, i procedure u pripremi kako pacijenta, ordinacije, pa i njih samih. Sve pohvale! 👏🏻",
        "languageCode": "hr"
      },
      "authorAttribution": {
        "displayName": "Aleksandra Dabović",
        "uri": "https://www.google.com/maps/contrib/118125428935765310951/reviews",
        "photoUri": "https://lh3.googleusercontent.com/a-/ALV-UjU6hUF6v71wET3B8TqxGtX6aSVQ_augg3apKbqwsXgNOlDznTkf3w=s128-c0x00000000-cc-rp-mo"
      },
      "publishTime": "2020-04-09T11:06:24.635308Z",
      "flagContentUri": "https://www.google.com/local/content/rap/report?postId=ChdDSUhNMG9nS0VJQ0FnSUNjeThPSDZ3RRAB&d=17924085&t=1",
      "googleMapsUri": "https://www.google.com/maps/reviews/data=!4m6!14m5!1m4!2m3!1sChdDSUhNMG9nS0VJQ0FnSUNjeThPSDZ3RRAB!2m1!1s0x134e73ff94e58ceb:0xaccacf4a69f37549"
    },
    {
      "name": "places/ChIJ64zllP9zThMRSXXzaUrPyqw/reviews/ChRDSUhNMG9nS0VJQ0FnSURoemRrNBAB",
      "relativePublishTimeDescription": "пре 3 године",
      "rating": 5,
      "text": {
        "text": "Волео сам услугу и пажњу.",
        "languageCode": "sr"
      },
      "originalText": {
        "text": "Me encanto el Trato y la atencion",
        "languageCode": "es"
      },
      "authorAttribution": {
        "displayName": "andrea",
        "uri": "https://www.google.com/maps/contrib/109384035234998198979/reviews",
        "photoUri": "https://lh3.googleusercontent.com/a/ACg8ocLYLC5xCCfaNsDbhPFAnJDPc9axitBXKBHgpr9_ElgM4zOxFQ=s128-c0x00000000-cc-rp-mo-ba3"
      },
      "publishTime": "2023-03-14T20:46:03.640003Z",
      "flagContentUri": "https://www.google.com/local/content/rap/report?postId=ChRDSUhNMG9nS0VJQ0FnSURoemRrNBAB&d=17924085&t=1",
      "googleMapsUri": "https://www.google.com/maps/reviews/data=!4m6!14m5!1m4!2m3!1sChRDSUhNMG9nS0VJQ0FnSURoemRrNBAB!2m1!1s0x134e73ff94e58ceb:0xaccacf4a69f37549"
    },
    {
      "name": "places/ChIJ64zllP9zThMRSXXzaUrPyqw/reviews/ChdDSUhNMG9nS0VJQ0FnSUR5OU1mbG9BRRAB",
      "relativePublishTimeDescription": "пре 5 година",
      "rating": 5,
      "text": {
        "text": "Најбољи зубар!",
        "languageCode": "sr"
      },
      "originalText": {
        "text": "Najbolji zubar!",
        "languageCode": "hr"
      },
      "authorAttribution": {
        "displayName": "Elvis Sijaric",
        "uri": "https://www.google.com/maps/contrib/114774694775377747859/reviews",
        "photoUri": "https://lh3.googleusercontent.com/a-/ALV-UjXUbknkocBrUImPwLr1WfrYwbESHfQDv6qD49ON4LTu43H9oAfs=s128-c0x00000000-cc-rp-mo"
      },
      "publishTime": "2021-02-26T09:20:26.417045Z",
      "flagContentUri": "https://www.google.com/local/content/rap/report?postId=ChdDSUhNMG9nS0VJQ0FnSUR5OU1mbG9BRRAB&d=17924085&t=1",
      "googleMapsUri": "https://www.google.com/maps/reviews/data=!4m6!14m5!1m4!2m3!1sChdDSUhNMG9nS0VJQ0FnSUR5OU1mbG9BRRAB!2m1!1s0x134e73ff94e58ceb:0xaccacf4a69f37549"
    },
    {
      "name": "places/ChIJ64zllP9zThMRSXXzaUrPyqw/reviews/Ci9DQUlRQUNvZENodHljRjlvT2twWWRETlVka2sxTkRFMk4wVTRkMGhTVDNkcFZWRRAB",
      "relativePublishTimeDescription": "пре месец дана",
      "rating": 5,
      "authorAttribution": {
        "displayName": "Valentina Sekulovic",
        "uri": "https://www.google.com/maps/contrib/107497837572277520325/reviews",
        "photoUri": "https://lh3.googleusercontent.com/a/ACg8ocJ9-SRlgEo0g3Xlk_pKK1p6PtwEgMCUeM7vs3WDHBKHoJMq-A=s128-c0x00000000-cc-rp-mo"
      },
      "publishTime": "2026-02-09T04:38:12.021849892Z",
      "flagContentUri": "https://www.google.com/local/content/rap/report?postId=Ci9DQUlRQUNvZENodHljRjlvT2twWWRETlVka2sxTkRFMk4wVTRkMGhTVDNkcFZWRRAB&d=17924085&t=1",
      "googleMapsUri": "https://www.google.com/maps/reviews/data=!4m6!14m5!1m4!2m3!1sCi9DQUlRQUNvZENodHljRjlvT2twWWRETlVka2sxTkRFMk4wVTRkMGhTVDNkcFZWRRAB!2m1!1s0x134e73ff94e58ceb:0xaccacf4a69f37549"
    }
  ],
  "_searchType": "dentist"
}