{
  "id": "ChdDSUhNMG9nS0VJQ0FnSUNjeTVTdmdnRRAB",
  "original_language": "hr",
  "text": "Sve pohvale za profesionalnost osoblja i poštovanje propisa u doba korona virusa ❤",
  "translations": {
    "sr": "Sve pohvale za profesionalnost osoblja i poštovanje propisa u doba korona virusa ❤",
    "sr_cyrl": "Све похвале за професионалност особља и поштовање прописа у доба корона вируса ❤",
    "en": "All praise for the professionalism of the staff and compliance with regulations during the coronavirus era ❤",
    "ru": "Все похвалы за профессионализм персонала и соблюдение правил во времена коронавируса ❤",
    "de": "Alles Lob für die Professionalität des Personals und die Einhaltung der Vorschriften in der Zeit des Coronavirus ❤",
    "tr": "Koronavirüs döneminde personelin profesyonelliği ve kurallara uyumu için tüm övgüler ❤"
  }
}
