{
  "id": "ChdDSUhNMG9nS0VJQ0FnSUMzNy0zOHlnRRAB",
  "original_language": "bs",
  "text": "Veoma profesionalni i ljubazni. Posle svake terapije bio sam kao nov. Sve preporuke!",
  "translations": {
    "sr": "Veoma profesionalni i ljubazni. Posle svake terapije bio sam kao nov. Sve preporuke!",
    "sr_cyrl": "Веома професионални и љубазни. После сваке терапије био сам као нов. Све препоруке!",
    "en": "Very professional and kind. After every therapy I felt like new. All recommendations!",
    "ru": "Очень профессиональные и доброжелательные. После каждой процедуры чувствовал себя как новый. Все рекомендации!",
    "de": "Sehr professionell und freundlich. Nach jeder Therapie fühlte ich mich wie neu. Alle Empfehlungen!",
    "tr": "Çok profesyonel ve nazik. Her terapiden sonra yepyeni gibi hissettim. Tüm tavsiyeler!"
  }
}
