{
  "type": "reply",
  "id": "ChZDSUhNMG9nS0VJQ0FnSUNjcThqSmVnEAE",
  "original_language": "en",
  "text": "Dear Andrea,\nthanks for this sincrear words.",
  "translations": {
    "en": "Dear Andrea,\nthanks for this sincrear words.",
    "sr": "Draga Andrea, hvala na ovim iskrenim rečima.",
    "sr_cyrl": "Драга Андреа, хвала на овим искреним речима.",
    "ru": "Дорогая Андреа, спасибо за эти искренние слова.",
    "de": "Liebe Andrea, danke für diese aufrichtigen Worte.",
    "tr": "Sevgili Andrea, bu içten sözler için teşekkürler."
  }
}
