{
  "id": "ChIJYalxn8GTUhMREtJseF9jpbk",
  "types": [
    "hospital",
    "point_of_interest",
    "health",
    "service",
    "establishment"
  ],
  "internationalPhoneNumber": "+382 69 451 190",
  "formattedAddress": "RVWF+XFP, Svetog Save, Беране, Црна Гора",
  "location": {
    "latitude": 42.847472499999995,
    "longitude": 19.8736879
  },
  "rating": 5,
  "googleMapsUri": "https://maps.google.com/?cid=13377207529867366930&g_mp=Cilnb29nbGUubWFwcy5wbGFjZXMudjEuUGxhY2VzLlNlYXJjaE5lYXJieRACGAQgAA",
  "userRatingCount": 2,
  "displayName": {
    "text": "Стоматолошка ординација \"Др РАДОЈЕВИЋ\"",
    "languageCode": "sr"
  },
  "reviews": [
    {
      "name": "places/ChIJYalxn8GTUhMREtJseF9jpbk/reviews/Ci9DQUlRQUNvZENodHljRjlvT2xCeGEydE9TalJxTFRFNWRWWlFaMDVCWVVKT1VsRRAB",
      "relativePublishTimeDescription": "пре 7 месеци",
      "rating": 5,
      "authorAttribution": {
        "displayName": "Sandra Boskovic",
        "uri": "https://www.google.com/maps/contrib/113045289528972722591/reviews",
        "photoUri": "https://lh3.googleusercontent.com/a/ACg8ocIl61K0yHk7heCnriGBf7anboyh5JV6w6ymXVOsL1Fr4qfi4KE=s128-c0x00000000-cc-rp-mo"
      },
      "publishTime": "2025-08-09T15:22:21.504035168Z",
      "flagContentUri": "https://www.google.com/local/content/rap/report?postId=Ci9DQUlRQUNvZENodHljRjlvT2xCeGEydE9TalJxTFRFNWRWWlFaMDVCWVVKT1VsRRAB&d=17924085&t=1",
      "googleMapsUri": "https://www.google.com/maps/reviews/data=!4m6!14m5!1m4!2m3!1sCi9DQUlRQUNvZENodHljRjlvT2xCeGEydE9TalJxTFRFNWRWWlFaMDVCWVVKT1VsRRAB!2m1!1s0x135293c19f71a961:0xb9a5635f786cd212"
    },
    {
      "name": "places/ChIJYalxn8GTUhMREtJseF9jpbk/reviews/ChdDSUhNMG9nS0VJQ0FnSUQtdXZfTmpBRRAB",
      "relativePublishTimeDescription": "пре 3 године",
      "rating": 5,
      "authorAttribution": {
        "displayName": "Luka Radojevic",
        "uri": "https://www.google.com/maps/contrib/114699081780586353820/reviews",
        "photoUri": "https://lh3.googleusercontent.com/a-/ALV-UjW4Z_vF4MqcZ6ld__-kuSNucgX12h2ZAsCU0A6IoS3XZ6jWnGPx=s128-c0x00000000-cc-rp-mo"
      },
      "publishTime": "2022-11-27T21:43:30.043345Z",
      "flagContentUri": "https://www.google.com/local/content/rap/report?postId=ChdDSUhNMG9nS0VJQ0FnSUQtdXZfTmpBRRAB&d=17924085&t=1",
      "googleMapsUri": "https://www.google.com/maps/reviews/data=!4m6!14m5!1m4!2m3!1sChdDSUhNMG9nS0VJQ0FnSUQtdXZfTmpBRRAB!2m1!1s0x135293c19f71a961:0xb9a5635f786cd212"
    }
  ],
  "_searchType": "hospital"
}